Metadata-Version: 2.1
Name: iust-ai-authenticator
Version: 0.1.0
Summary: A library for authenticating AI course submissions at IUST
License: MIT
Author: MSNp
Author-email: mohamadnematpoor@gmail.com
Requires-Python: >=3.11,<4.0
Classifier: License :: OSI Approved :: MIT License
Classifier: Programming Language :: Python :: 3
Classifier: Programming Language :: Python :: 3.11
Classifier: Programming Language :: Python :: 3.12
Requires-Dist: numpy (>=2.1.1,<3.0.0)
Requires-Dist: pandas (>=2.2.3,<3.0.0)
